{"cameraMode":{"drawMode":0,"name":"Shaded","section":"Shading Mode"},"sceneLighting":true,"audioPlay":false,"sceneViewState":{"m_AlwaysRefresh":false,"showFog":true,"showSkybox":true,"showFlares":true,"showImageEffects":true,"showParticleSystems":true,"showVisualEffectGraphs":true,"m_FxEnabled":true},"in2DMode":false,"pivot":{"x":3.0,"y":1.2000001668930054,"z":-3.0},"rotation":{"x":0.11345086246728897,"y":-0.6063914895057678,"z":0.08987820148468018,"w":0.7816789746284485},"size":1.868329405784607,"orthographic":false}